ckanext/__init__.py
ckanext/geoview/__init__.py
ckanext/geoview/plugin.py
ckanext/geoview/utils.py
ckanext/geoview/views.py
ckanext/geoview/public/resource.config
ckanext/geoview/public/webassets.yml
ckanext/geoview/public/css/geo-resource-styles.css
ckanext/geoview/public/css/geojson_preview.css
ckanext/geoview/public/css/ol_preview.css
ckanext/geoview/public/css/shp_preview.css
ckanext/geoview/public/css/wmts_preview.css
ckanext/geoview/public/img/blank.gif
ckanext/geoview/public/img/gis-resources-sprite-icons.png
ckanext/geoview/public/js/common_map.js
ckanext/geoview/public/js/geojson_preview.js
ckanext/geoview/public/js/ol_preview.js
ckanext/geoview/public/js/shp_preview.js
ckanext/geoview/public/js/wmts_preview.js
ckanext/geoview/public/js/vendor/jszip/jszip.min.js
ckanext/geoview/public/js/vendor/jszip-utils/jszip-utils.min.js
ckanext/geoview/public/js/vendor/leaflet/leaflet.css
ckanext/geoview/public/js/vendor/leaflet/leaflet.js
ckanext/geoview/public/js/vendor/leaflet/images/layers-2x.png
ckanext/geoview/public/js/vendor/leaflet/images/layers.png
ckanext/geoview/public/js/vendor/leaflet/images/marker-icon-2x.png
ckanext/geoview/public/js/vendor/leaflet/images/marker-icon.png
ckanext/geoview/public/js/vendor/leaflet/images/marker-shadow.png
ckanext/geoview/public/js/vendor/leaflet-providers/leaflet-providers.js
ckanext/geoview/public/js/vendor/leaflet-spin/leaflet.spin.js
ckanext/geoview/public/js/vendor/ol-helpers/ol-helpers.css
ckanext/geoview/public/js/vendor/ol-helpers/ol-helpers.js
ckanext/geoview/public/js/vendor/ol-helpers/ol-helpers.less
ckanext/geoview/public/js/vendor/ol-helpers/ol-layer-switcher.js
ckanext/geoview/public/js/vendor/openlayers/ol.css
ckanext/geoview/public/js/vendor/openlayers/ol.js
ckanext/geoview/public/js/vendor/proj4/proj4.js
ckanext/geoview/public/js/vendor/proj4leaflet/proj4leaflet.js
ckanext/geoview/public/js/vendor/shp2geojson/preprocess.js
ckanext/geoview/public/js/vendor/shp2geojson/preview.js
ckanext_geoview-0.3.1.dist-info/licenses/LICENSE
ckanext_geoview-0.3.1.dist-info/METADATA
ckanext_geoview-0.3.1.dist-info/WHEEL
ckanext_geoview-0.3.1.dist-info/entry_points.txt
ckanext_geoview-0.3.1.dist-info/top_level.txt
ckanext_geoview-0.3.1.dist-info/RECORD
