Metadata-Version: 2.4
Name: ckanext-geoview
Version: 0.3.1
Summary: Geospatial viewers for CKAN resources
Author-email: "Philippe Duchesne, Adrià Mercader and contributors" <tech-team@ckan.org>
Maintainer-email: CKAN Tech Team and contributors <tech-team@ckan.org>
License: MIT
Project-URL: Repository, https://github.com/ckan/ckanext-geoview
Project-URL: Issues, https://github.com/ckan/ckanext-geoview/issues
Keywords: ckan,ckanext,geospatial,openlayers,leaflet,wms,wfs,geojson
Classifier: Intended Audience :: Developers
Classifier: Development Status :: 5 - Production/Stable
Classifier: License :: OSI Approved :: MIT License
Classifier: Programming Language :: Python :: 3.9
Classifier: Programming Language :: Python :: 3.10
Classifier: Programming Language :: Python :: 3.11
Classifier: Programming Language :: Python :: 3.12
Classifier: Programming Language :: Python :: 3.13
License-File: LICENSE
Dynamic: license-file
